setup.py
constants_py.egg-info/PKG-INFO
constants_py.egg-info/SOURCES.txt
constants_py.egg-info/dependency_links.txt
constants_py.egg-info/requires.txt
constants_py.egg-info/top_level.txt
pyConstants/__init__.py
pyConstants/constantBase.py
pyConstants/constantWrappers.py
pyConstants/test.py