Metadata-Version: 2.1
Name: constants-py
Version: 1.0.4
Summary: Allows for the creation of constants in Python
Author: LCreations
Classifier: Programming Language :: Python :: 3
Classifier: License :: OSI Approved :: MIT License
Classifier: Operating System :: OS Independent
Requires-Python: >=3.6
Requires-Dist: colorama
